{
    "os": "Linux-4.15.0-112-generic-x86_64-with-glibc2.27",
    "python": "3.10.9",
    "heartbeatAt": "2023-03-19T09:09:52.351730",
    "startedAt": "2023-03-19T09:09:51.597692",
    "docker": null,
    "cuda": null,
    "args": [],
    "state": "running",
    "program": "/home/yerinyoon/code/anonymousNet/starGAN/stargan.py",
    "codePath": "starGAN/stargan.py",
    "git": {
        "remote": "https://github.com/yoonyerin/anonymousNet.git",
        "commit": "4f097ac8a7f6a34f4425af7538323086b20e6742"
    },
    "email": "yerinyoon@ewhain.net",
    "root": "/home/yerinyoon/code/anonymousNet",
    "host": "ubuntu",
    "username": "yerinyoon",
    "executable": "/home/yerinyoon/anaconda3/envs/pytorch/bin/python",
    "cpu_count": 56,
    "cpu_count_logical": 112,
    "cpu_freq": {
        "current": 1145.7049285714286,
        "min": 800.0,
        "max": 2601.0
    },
    "cpu_freq_per_core": [
        {
            "current": 800.783,
            "min": 800.0,
            "max": 2601.0
        },
        {
            "current": 801.663,
            "min": 800.0,
            "max": 2601.0
        },
        {
            "current": 1127.225,
            "min": 800.0,
            "max": 2601.0
        },
        {
            "current": 800.847,
            "min": 800.0,
            "max": 2601.0
        },
        {
            "current": 801.225,
            "min": 800.0,
            "max": 2601.0
        },
        {
            "current": 1087.091,
            "min": 800.0,
            "max": 2601.0
        },
        {
            "current": 1473.123,
            "min": 800.0,
            "max": 2601.0
        },
        {
            "current": 801.608,
            "min": 800.0,
            "max": 2601.0
        },
        {
            "current": 1148.653,
            "min": 800.0,
            "max": 2601.0
        },
        {
            "current": 800.414,
            "min": 800.0,
            "max": 2601.0
        },
        {
            "current": 801.68,
            "min": 800.0,
            "max": 2601.0
        },
        {
            "current": 850.261,
            "min": 800.0,
            "max": 2601.0
        },
        {
            "current": 1091.125,
            "min": 800.0,
            "max": 2601.0
        },
        {
            "current": 987.699,
            "min": 800.0,
            "max": 2601.0
        },
        {
            "current": 801.235,
            "min": 800.0,
            "max": 2601.0
        },
        {
            "current": 800.806,
            "min": 800.0,
            "max": 2601.0
        },
        {
            "current": 1069.935,
            "min": 800.0,
            "max": 2601.0
        },
        {
            "current": 801.21,
            "min": 800.0,
            "max": 2601.0
        },
        {
            "current": 1150.0,
            "min": 800.0,
            "max": 2601.0
        },
        {
            "current": 800.819,
            "min": 800.0,
            "max": 2601.0
        },
        {
            "current": 800.421,
            "min": 800.0,
            "max": 2601.0
        },
        {
            "current": 800.824,
            "min": 800.0,
            "max": 2601.0
        },
        {
            "current": 800.809,
            "min": 800.0,
            "max": 2601.0
        },
        {
            "current": 1070.969,
            "min": 800.0,
            "max": 2601.0
        },
        {
            "current": 791.443,
            "min": 800.0,
            "max": 2601.0
        },
        {
            "current": 800.829,
            "min": 800.0,
            "max": 2601.0
        },
        {
            "current": 800.826,
            "min": 800.0,
            "max": 2601.0
        },
        {
            "current": 1121.456,
            "min": 800.0,
            "max": 2601.0
        },
        {
            "current": 900.985,
            "min": 800.0,
            "max": 2601.0
        },
        {
            "current": 819.767,
            "min": 800.0,
            "max": 2601.0
        },
        {
            "current": 1636.733,
            "min": 800.0,
            "max": 2601.0
        },
        {
            "current": 800.438,
            "min": 800.0,
            "max": 2601.0
        },
        {
            "current": 801.254,
            "min": 800.0,
            "max": 2601.0
        },
        {
            "current": 800.866,
            "min": 800.0,
            "max": 2601.0
        },
        {
            "current": 800.874,
            "min": 800.0,
            "max": 2601.0
        },
        {
            "current": 949.031,
            "min": 800.0,
            "max": 2601.0
        },
        {
            "current": 800.855,
            "min": 800.0,
            "max": 2601.0
        },
        {
            "current": 800.872,
            "min": 800.0,
            "max": 2601.0
        },
        {
            "current": 1060.561,
            "min": 800.0,
            "max": 2601.0
        },
        {
            "current": 1673.43,
            "min": 800.0,
            "max": 2601.0
        },
        {
            "current": 800.854,
            "min": 800.0,
            "max": 2601.0
        },
        {
            "current": 2600.0,
            "min": 800.0,
            "max": 2601.0
        },
        {
            "current": 800.843,
            "min": 800.0,
            "max": 2601.0
        },
        {
            "current": 801.213,
            "min": 800.0,
            "max": 2601.0
        },
        {
            "current": 801.323,
            "min": 800.0,
            "max": 2601.0
        },
        {
            "current": 2597.653,
            "min": 800.0,
            "max": 2601.0
        },
        {
            "current": 1501.815,
            "min": 800.0,
            "max": 2601.0
        },
        {
            "current": 800.868,
            "min": 800.0,
            "max": 2601.0
        },
        {
            "current": 801.31,
            "min": 800.0,
            "max": 2601.0
        },
        {
            "current": 2602.254,
            "min": 800.0,
            "max": 2601.0
        },
        {
            "current": 801.233,
            "min": 800.0,
            "max": 2601.0
        },
        {
            "current": 800.87,
            "min": 800.0,
            "max": 2601.0
        },
        {
            "current": 1135.447,
            "min": 800.0,
            "max": 2601.0
        },
        {
            "current": 800.854,
            "min": 800.0,
            "max": 2601.0
        },
        {
            "current": 1506.911,
            "min": 800.0,
            "max": 2601.0
        },
        {
            "current": 800.388,
            "min": 800.0,
            "max": 2601.0
        },
        {
            "current": 801.616,
            "min": 800.0,
            "max": 2601.0
        },
        {
            "current": 801.7,
            "min": 800.0,
            "max": 2601.0
        },
        {
            "current": 801.287,
            "min": 800.0,
            "max": 2601.0
        },
        {
            "current": 800.43,
            "min": 800.0,
            "max": 2601.0
        },
        {
            "current": 800.458,
            "min": 800.0,
            "max": 2601.0
        },
        {
            "current": 1456.122,
            "min": 800.0,
            "max": 2601.0
        },
        {
            "current": 866.972,
            "min": 800.0,
            "max": 2601.0
        },
        {
            "current": 801.632,
            "min": 800.0,
            "max": 2601.0
        },
        {
            "current": 941.392,
            "min": 800.0,
            "max": 2601.0
        },
        {
            "current": 800.855,
            "min": 800.0,
            "max": 2601.0
        },
        {
            "current": 800.867,
            "min": 800.0,
            "max": 2601.0
        },
        {
            "current": 900.996,
            "min": 800.0,
            "max": 2601.0
        },
        {
            "current": 801.681,
            "min": 800.0,
            "max": 2601.0
        },
        {
            "current": 2602.336,
            "min": 800.0,
            "max": 2601.0
        },
        {
            "current": 801.269,
            "min": 800.0,
            "max": 2601.0
        },
        {
            "current": 845.123,
            "min": 800.0,
            "max": 2601.0
        },
        {
            "current": 1066.082,
            "min": 800.0,
            "max": 2601.0
        },
        {
            "current": 800.834,
            "min": 800.0,
            "max": 2601.0
        },
        {
            "current": 800.874,
            "min": 800.0,
            "max": 2601.0
        },
        {
            "current": 801.287,
            "min": 800.0,
            "max": 2601.0
        },
        {
            "current": 800.869,
            "min": 800.0,
            "max": 2601.0
        },
        {
            "current": 800.858,
            "min": 800.0,
            "max": 2601.0
        },
        {
            "current": 800.634,
            "min": 800.0,
            "max": 2601.0
        },
        {
            "current": 875.035,
            "min": 800.0,
            "max": 2601.0
        },
        {
            "current": 801.286,
            "min": 800.0,
            "max": 2601.0
        },
        {
            "current": 800.846,
            "min": 800.0,
            "max": 2601.0
        },
        {
            "current": 826.017,
            "min": 800.0,
            "max": 2601.0
        },
        {
            "current": 2600.0,
            "min": 800.0,
            "max": 2601.0
        },
        {
            "current": 2602.192,
            "min": 800.0,
            "max": 2601.0
        },
        {
            "current": 865.717,
            "min": 800.0,
            "max": 2601.0
        },
        {
            "current": 1049.422,
            "min": 800.0,
            "max": 2601.0
        },
        {
            "current": 2602.574,
            "min": 800.0,
            "max": 2601.0
        },
        {
            "current": 1321.649,
            "min": 800.0,
            "max": 2601.0
        },
        {
            "current": 2602.549,
            "min": 800.0,
            "max": 2601.0
        },
        {
            "current": 800.898,
            "min": 800.0,
            "max": 2601.0
        },
        {
            "current": 2088.73,
            "min": 800.0,
            "max": 2601.0
        },
        {
            "current": 800.865,
            "min": 800.0,
            "max": 2601.0
        },
        {
            "current": 800.843,
            "min": 800.0,
            "max": 2601.0
        },
        {
            "current": 1232.759,
            "min": 800.0,
            "max": 2601.0
        },
        {
            "current": 2077.38,
            "min": 800.0,
            "max": 2601.0
        },
        {
            "current": 800.865,
            "min": 800.0,
            "max": 2601.0
        },
        {
            "current": 2600.0,
            "min": 800.0,
            "max": 2601.0
        },
        {
            "current": 2604.655,
            "min": 800.0,
            "max": 2601.0
        },
        {
            "current": 1101.363,
            "min": 800.0,
            "max": 2601.0
        },
        {
            "current": 876.112,
            "min": 800.0,
            "max": 2601.0
        },
        {
            "current": 1436.886,
            "min": 800.0,
            "max": 2601.0
        },
        {
            "current": 1200.0,
            "min": 800.0,
            "max": 2601.0
        },
        {
            "current": 801.344,
            "min": 800.0,
            "max": 2601.0
        },
        {
            "current": 1011.549,
            "min": 800.0,
            "max": 2601.0
        },
        {
            "current": 800.853,
            "min": 800.0,
            "max": 2601.0
        },
        {
            "current": 1152.011,
            "min": 800.0,
            "max": 2601.0
        },
        {
            "current": 800.895,
            "min": 800.0,
            "max": 2601.0
        },
        {
            "current": 800.853,
            "min": 800.0,
            "max": 2601.0
        },
        {
            "current": 2602.459,
            "min": 800.0,
            "max": 2601.0
        },
        {
            "current": 1524.838,
            "min": 800.0,
            "max": 2601.0
        },
        {
            "current": 800.423,
            "min": 800.0,
            "max": 2601.0
        }
    ],
    "disk": {
        "total": 1802.3645973205566,
        "used": 228.54578399658203
    },
    "gpu": "NVIDIA RTX A6000",
    "gpu_count": 3,
    "gpu_devices": [
        {
            "name": "NVIDIA RTX A6000",
            "memory_total": 51050315776
        },
        {
            "name": "NVIDIA RTX A6000",
            "memory_total": 47848357888
        },
        {
            "name": "NVIDIA RTX A6000",
            "memory_total": 51050315776
        }
    ],
    "memory": {
        "total": 251.5168571472168
    }
}
