{
    "os": "Linux-4.15.0-112-generic-x86_64-with-glibc2.27",
    "python": "3.10.9",
    "heartbeatAt": "2023-04-04T09:03:12.100119",
    "startedAt": "2023-04-04T09:03:11.398543",
    "docker": null,
    "cuda": null,
    "args": [
        "--mode",
        "train "
    ],
    "state": "running",
    "program": "/home/yerinyoon/code/anonymousNet/starGAN/stargan.py",
    "codePath": "stargan.py",
    "git": {
        "remote": "https://github.com/yoonyerin/starGAN.git",
        "commit": "b4306af6dc1768aee0aff000851fd29a52e619c8"
    },
    "email": "yerinyoon@ewhain.net",
    "root": "/home/yerinyoon/code/anonymousNet/starGAN",
    "host": "ubuntu",
    "username": "yerinyoon",
    "executable": "/home/yerinyoon/anaconda3/envs/pytorch/bin/python",
    "cpu_count": 56,
    "cpu_count_logical": 112,
    "cpu_freq": {
        "current": 1019.4682500000002,
        "min": 800.0,
        "max": 2601.0
    },
    "cpu_freq_per_core": [
        {
            "current": 800.782,
            "min": 800.0,
            "max": 2601.0
        },
        {
            "current": 801.287,
            "min": 800.0,
            "max": 2601.0
        },
        {
            "current": 817.483,
            "min": 800.0,
            "max": 2601.0
        },
        {
            "current": 800.856,
            "min": 800.0,
            "max": 2601.0
        },
        {
            "current": 801.647,
            "min": 800.0,
            "max": 2601.0
        },
        {
            "current": 800.857,
            "min": 800.0,
            "max": 2601.0
        },
        {
            "current": 800.856,
            "min": 800.0,
            "max": 2601.0
        },
        {
            "current": 801.21,
            "min": 800.0,
            "max": 2601.0
        },
        {
            "current": 801.253,
            "min": 800.0,
            "max": 2601.0
        },
        {
            "current": 800.859,
            "min": 800.0,
            "max": 2601.0
        },
        {
            "current": 801.312,
            "min": 800.0,
            "max": 2601.0
        },
        {
            "current": 800.418,
            "min": 800.0,
            "max": 2601.0
        },
        {
            "current": 801.709,
            "min": 800.0,
            "max": 2601.0
        },
        {
            "current": 800.18,
            "min": 800.0,
            "max": 2601.0
        },
        {
            "current": 800.855,
            "min": 800.0,
            "max": 2601.0
        },
        {
            "current": 1062.255,
            "min": 800.0,
            "max": 2601.0
        },
        {
            "current": 801.288,
            "min": 800.0,
            "max": 2601.0
        },
        {
            "current": 801.249,
            "min": 800.0,
            "max": 2601.0
        },
        {
            "current": 800.149,
            "min": 800.0,
            "max": 2601.0
        },
        {
            "current": 853.632,
            "min": 800.0,
            "max": 2601.0
        },
        {
            "current": 800.852,
            "min": 800.0,
            "max": 2601.0
        },
        {
            "current": 801.671,
            "min": 800.0,
            "max": 2601.0
        },
        {
            "current": 816.666,
            "min": 800.0,
            "max": 2601.0
        },
        {
            "current": 2600.0,
            "min": 800.0,
            "max": 2601.0
        },
        {
            "current": 800.304,
            "min": 800.0,
            "max": 2601.0
        },
        {
            "current": 800.835,
            "min": 800.0,
            "max": 2601.0
        },
        {
            "current": 800.852,
            "min": 800.0,
            "max": 2601.0
        },
        {
            "current": 801.237,
            "min": 800.0,
            "max": 2601.0
        },
        {
            "current": 800.768,
            "min": 800.0,
            "max": 2601.0
        },
        {
            "current": 801.183,
            "min": 800.0,
            "max": 2601.0
        },
        {
            "current": 801.234,
            "min": 800.0,
            "max": 2601.0
        },
        {
            "current": 979.699,
            "min": 800.0,
            "max": 2601.0
        },
        {
            "current": 800.813,
            "min": 800.0,
            "max": 2601.0
        },
        {
            "current": 824.172,
            "min": 800.0,
            "max": 2601.0
        },
        {
            "current": 885.383,
            "min": 800.0,
            "max": 2601.0
        },
        {
            "current": 800.792,
            "min": 800.0,
            "max": 2601.0
        },
        {
            "current": 822.715,
            "min": 800.0,
            "max": 2601.0
        },
        {
            "current": 800.84,
            "min": 800.0,
            "max": 2601.0
        },
        {
            "current": 1048.217,
            "min": 800.0,
            "max": 2601.0
        },
        {
            "current": 2602.227,
            "min": 800.0,
            "max": 2601.0
        },
        {
            "current": 801.246,
            "min": 800.0,
            "max": 2601.0
        },
        {
            "current": 1085.014,
            "min": 800.0,
            "max": 2601.0
        },
        {
            "current": 801.192,
            "min": 800.0,
            "max": 2601.0
        },
        {
            "current": 2600.0,
            "min": 800.0,
            "max": 2601.0
        },
        {
            "current": 977.457,
            "min": 800.0,
            "max": 2601.0
        },
        {
            "current": 800.841,
            "min": 800.0,
            "max": 2601.0
        },
        {
            "current": 828.034,
            "min": 800.0,
            "max": 2601.0
        },
        {
            "current": 1432.757,
            "min": 800.0,
            "max": 2601.0
        },
        {
            "current": 801.267,
            "min": 800.0,
            "max": 2601.0
        },
        {
            "current": 800.816,
            "min": 800.0,
            "max": 2601.0
        },
        {
            "current": 1078.754,
            "min": 800.0,
            "max": 2601.0
        },
        {
            "current": 901.003,
            "min": 800.0,
            "max": 2601.0
        },
        {
            "current": 900.973,
            "min": 800.0,
            "max": 2601.0
        },
        {
            "current": 801.24,
            "min": 800.0,
            "max": 2601.0
        },
        {
            "current": 800.82,
            "min": 800.0,
            "max": 2601.0
        },
        {
            "current": 800.79,
            "min": 800.0,
            "max": 2601.0
        },
        {
            "current": 801.668,
            "min": 800.0,
            "max": 2601.0
        },
        {
            "current": 801.323,
            "min": 800.0,
            "max": 2601.0
        },
        {
            "current": 800.438,
            "min": 800.0,
            "max": 2601.0
        },
        {
            "current": 800.89,
            "min": 800.0,
            "max": 2601.0
        },
        {
            "current": 801.286,
            "min": 800.0,
            "max": 2601.0
        },
        {
            "current": 1513.412,
            "min": 800.0,
            "max": 2601.0
        },
        {
            "current": 800.902,
            "min": 800.0,
            "max": 2601.0
        },
        {
            "current": 854.57,
            "min": 800.0,
            "max": 2601.0
        },
        {
            "current": 906.297,
            "min": 800.0,
            "max": 2601.0
        },
        {
            "current": 801.327,
            "min": 800.0,
            "max": 2601.0
        },
        {
            "current": 801.343,
            "min": 800.0,
            "max": 2601.0
        },
        {
            "current": 3496.65,
            "min": 800.0,
            "max": 2601.0
        },
        {
            "current": 801.288,
            "min": 800.0,
            "max": 2601.0
        },
        {
            "current": 800.078,
            "min": 800.0,
            "max": 2601.0
        },
        {
            "current": 800.867,
            "min": 800.0,
            "max": 2601.0
        },
        {
            "current": 1433.582,
            "min": 800.0,
            "max": 2601.0
        },
        {
            "current": 800.877,
            "min": 800.0,
            "max": 2601.0
        },
        {
            "current": 800.419,
            "min": 800.0,
            "max": 2601.0
        },
        {
            "current": 800.892,
            "min": 800.0,
            "max": 2601.0
        },
        {
            "current": 800.869,
            "min": 800.0,
            "max": 2601.0
        },
        {
            "current": 800.894,
            "min": 800.0,
            "max": 2601.0
        },
        {
            "current": 2602.414,
            "min": 800.0,
            "max": 2601.0
        },
        {
            "current": 841.98,
            "min": 800.0,
            "max": 2601.0
        },
        {
            "current": 2600.0,
            "min": 800.0,
            "max": 2601.0
        },
        {
            "current": 800.871,
            "min": 800.0,
            "max": 2601.0
        },
        {
            "current": 800.443,
            "min": 800.0,
            "max": 2601.0
        },
        {
            "current": 800.869,
            "min": 800.0,
            "max": 2601.0
        },
        {
            "current": 800.842,
            "min": 800.0,
            "max": 2601.0
        },
        {
            "current": 801.567,
            "min": 800.0,
            "max": 2601.0
        },
        {
            "current": 801.641,
            "min": 800.0,
            "max": 2601.0
        },
        {
            "current": 825.631,
            "min": 800.0,
            "max": 2601.0
        },
        {
            "current": 800.866,
            "min": 800.0,
            "max": 2601.0
        },
        {
            "current": 801.254,
            "min": 800.0,
            "max": 2601.0
        },
        {
            "current": 800.421,
            "min": 800.0,
            "max": 2601.0
        },
        {
            "current": 857.142,
            "min": 800.0,
            "max": 2601.0
        },
        {
            "current": 801.22,
            "min": 800.0,
            "max": 2601.0
        },
        {
            "current": 801.263,
            "min": 800.0,
            "max": 2601.0
        },
        {
            "current": 800.847,
            "min": 800.0,
            "max": 2601.0
        },
        {
            "current": 1507.223,
            "min": 800.0,
            "max": 2601.0
        },
        {
            "current": 1100.687,
            "min": 800.0,
            "max": 2601.0
        },
        {
            "current": 801.252,
            "min": 800.0,
            "max": 2601.0
        },
        {
            "current": 800.857,
            "min": 800.0,
            "max": 2601.0
        },
        {
            "current": 1110.529,
            "min": 800.0,
            "max": 2601.0
        },
        {
            "current": 2600.0,
            "min": 800.0,
            "max": 2601.0
        },
        {
            "current": 800.873,
            "min": 800.0,
            "max": 2601.0
        },
        {
            "current": 801.286,
            "min": 800.0,
            "max": 2601.0
        },
        {
            "current": 837.203,
            "min": 800.0,
            "max": 2601.0
        },
        {
            "current": 2602.411,
            "min": 800.0,
            "max": 2601.0
        },
        {
            "current": 2507.87,
            "min": 800.0,
            "max": 2601.0
        },
        {
            "current": 800.845,
            "min": 800.0,
            "max": 2601.0
        },
        {
            "current": 800.825,
            "min": 800.0,
            "max": 2601.0
        },
        {
            "current": 901.036,
            "min": 800.0,
            "max": 2601.0
        },
        {
            "current": 801.231,
            "min": 800.0,
            "max": 2601.0
        },
        {
            "current": 801.246,
            "min": 800.0,
            "max": 2601.0
        },
        {
            "current": 1910.078,
            "min": 800.0,
            "max": 2601.0
        },
        {
            "current": 801.644,
            "min": 800.0,
            "max": 2601.0
        }
    ],
    "disk": {
        "total": 1802.3645973205566,
        "used": 537.0448608398438
    },
    "gpu": "NVIDIA RTX A6000",
    "gpu_count": 3,
    "gpu_devices": [
        {
            "name": "NVIDIA RTX A6000",
            "memory_total": 51050315776
        },
        {
            "name": "NVIDIA RTX A6000",
            "memory_total": 47848357888
        },
        {
            "name": "NVIDIA RTX A6000",
            "memory_total": 51050315776
        }
    ],
    "memory": {
        "total": 251.5168571472168
    }
}
